truesight/__init__.py
truesight/__main__.py
truesight/config/__init__.py
truesight/config/loader.py
truesight/config/worker.py
truesight/lib/__init__.py
truesight/lib/auto.py
truesight/logger/__init__.py
truesight/logger/handler.py
truesight/network/__init__.py
truesight/network/external/__init__.py
truesight/network/external/http.py
truesightlib-0.1.0.dist-info/METADATA
truesightlib-0.1.0.dist-info/WHEEL
truesightlib-0.1.0.dist-info/top_level.txt
truesightlib-0.1.0.dist-info/RECORD
