Metadata-Version: 2.4
Name: truesightlib
Version: 0.1.0
Summary: TrueSight SDK for logs, metrics and observability
Author: The brothers
License: MIT
Project-URL: Homepage, https://codeberg.org/drxw/vectorial_sdk
Requires-Python: >=3.11
Requires-Dist: pyyaml>=6.0.3
Requires-Dist: requests>=2.32.5
Provides-Extra: dev
Requires-Dist: build>=1.3.0; extra == "dev"
Requires-Dist: twine>=6.2.0; extra == "dev"
